emon_worker_m8/__init__.py
emon_worker_m8/delta_structure.py
emon_worker_m8/emon_data_helper.py
emon_worker_m8/emoncms_api.py
emon_worker_m8/emoncms_app.py
emon_worker_m8/emoncms_set_api.py
emon_worker_m8/emoncms_structure.py
emon_worker_m8/emoncms_worker.py
test/__init__.py
emon_worker_m8-0.0.2.dist-info/LICENSE
emon_worker_m8-0.0.2.dist-info/METADATA
emon_worker_m8-0.0.2.dist-info/WHEEL
emon_worker_m8-0.0.2.dist-info/top_level.txt
emon_worker_m8-0.0.2.dist-info/RECORD
